{
  "g_16c73a": "Please select items to save.",
  "g_e03450": "Please confirm 🙏",
  "g_b040a8": " changes saved",
  "g_314edd": "Are you sure you want to delete this membership type?",
  "g_0f2027": "Deleted.",
  "g_fb06e1": "An error occurred while saving.",
  "g_2e8547": "New Membership",
  "g_02ad8a": "Enter membership name.",
  "g_d201d1": "Saved.",
  "g_504690": "Save Failed",
  "g_6a7ffd": "Error Occurred",
  "g_8f6098": "Loading pricing info...",
  "g_c34bb1": "Manage Pricing",
  "g_51b906": "Add New Pricing",
  "g_10fe8e": "What is Data Reset?",
  "g_9b7986": "Clears previously added/edited pricing and reverts to the standard pricing template provided by PassFlow Ai",
  "g_5bec6f": "Standard Pricing Template (Advanced, General, Hatha Intensive, Kids Flying)",
  "g_4ce3cf": ".",
  "g_465990": "* E.g., General 1-pass 25,000 KRW, Advanced 1-pass 35,000 KRW (Based on average studio market prices)",
  "g_a82ac8": "Do you want to restore pricing to initial data?\n(All existing pricing will be deleted and overwritten with default values)",
  "g_afd4b7": "Failed: ",
  "g_8c7db7": "Error: ",
  "g_f09048": "Reset Pricing",
  "g_1e6a4a": "No Name",
  "g_9bf7b8": "No Option Name",
  "g_f7b7b3": "3 Months",
  "g_eba921": "(Cash ",
  "g_128a5e": "6 Months",
  "g_c103da": "Edit Membership",
  "g_af6ee2": "Membership Name",
  "g_9ad5ed": "Apply Branch",
  "g_372c01": "Details Option (Duration/Passes)",
  "g_7f7442": "+ Add Option",
  "g_7be993": "Display Name",
  "g_450c9f": "E.g.: 1 Month (2/week)",
  "g_9689df": "Base Price",
  "g_d1d84b": "Passes (Unlimited=9999)",
  "g_56ec9a": "Validity (Months)",
  "g_80577c": "Type",
  "g_7fa668": "Duration (Monthly)",
  "g_a59218": "Pass-based",
  "g_6c4f74": "3-Month Discount Price (Optional)",
  "g_6f5659": "If empty, defaultx3",
  "g_1373c8": "6-Month Discount Price (Optional)",
  "g_1968e9": "If empty, defaultx6",
  "g_33c05f": "💰 Cash/Transfer Price (Optional)",
  "g_be7bd5": "Fixed Cash Price",
  "g_b569d0": "Auto-discount if unset",
  "g_17be07": "Cash 3 Months",
  "g_d168f3": "Card price applied if unset",
  "g_262215": "Cash 6 Months",
  "g_426b6b": "* If empty, 5% discount off card price (3+ months) auto-applied",
  "g_fcbec0": "Save",
  "g_7d8f1b": "All Branches",
  "g_541ba0": "This Month Cumulative Revenue",
  "g_5860d4": "(New: ",
  "g_7c492c": "/ \n                                     Renewal: ",
  "g_fea767": "Revenue Generated Today",
  "g_4ad6b9": "Today's Revenue Standard",
  "g_462466": "Total amount of payments generated on the current date (as of midnight).",
  "g_04f3c7": "This Month Payment Count",
  "g_14f230": "Total Payment Count",
  "g_f5f17c": "Total number of approved payments generated this month.",
  "g_24e8ea": "📈 Daily Revenue (Last 14 Days)",
  "g_04835a": "📊 Monthly Revenue Trend (Last 6 Months)",
  "g_b982a3": "Entire Month",
  "g_a4b541": "Total Monthly Revenue",
  "g_0a8b86": "🏷️ Sales Status by Membership",
  "g_e15020": "New:",
  "g_664391": "Renewal:",
  "g_467a35": "Total",
  "g_ff51fe": "Special/Advanced",
  "g_31dd1a": " schedule is empty.",
  "g_ca9937": "No need to register one by one; simply copy last month's schedule to start easily.",
  "g_e2b9a9": "📥 Copy Last Month's Schedule as is",
  "g_bdd9af": "Prev Month",
  "g_b8a987": "Confirmed",
  "g_2ddd21": "TBD",
  "g_fbb7c8": "Next Month",
  "g_956383": "Restore Backup",
  "g_c771f7": " Backed up at",
  "g_20c52c": " class data items included",
  "g_67d4b4": "Most Recent",
  "g_3ad441": "Restore to this point",
  "g_bed297": "📸 Auto check-in when face is shown",
  "g_dda3b3": "📸 Tap to register face",
  "g_53d1a3": "🔐 Photo not saved · Encrypted into 128 numbers · Irreversible",
  "g_80a6d7": "AI is preparing today's message",
  "g_f63fa3": "Checking practice info...",
  "g_068637": "📸 Auto Check-in",
  "g_f0cdf8": "📸 Register Face",
  "g_dd1e5b": "✓ Check remaining passes",
  "g_fd3c41": "✓ View class schedule",
  "g_4bc4df": "✓ Get personalized alerts",
  "g_a03db7": "Checking in...",
  "g_9eb41e": "Please wait a moment",
  "g_43650b": "Preparing Check-in system...",
  "g_89d974": "Please enter the last 4 digits of your phone number",
  "g_f09d30": "Wait! You just checked in.",
  "g_deade2": "Did you come with ",
  "g_f8b91f": "family/friends",
  "g_c1961e": "?",
  "g_79ee03": "If not, please press the ",
  "g_cd2c50": "Red Button",
  "g_4d85bd": " below!",
  "g_89a5df": "😱 Oops, I pressed the wrong button!",
  "g_8c1d37": "(Cancel Check-in)",
  "g_2145a5": "🙆♀️ Yes, it's for two people",
  "g_0c569e": "(Companion Check-in)",
  "g_4bf474": "If you don't press anything, it will automatically ",
  "g_38f886": " seconds later ",
  "g_d03d76": "Process Check-in",
  "g_5c5d7c": ".",
  "g_4c0a1c": "Preparing camera...",
  "g_8b19cb": "Cannot access camera. Please check camera permissions.",
  "g_9a762b": "No registered member found. Please check the number.",
  "g_9f1598": "Problem occurred during member lookup. Please try again.",
  "g_7c5758": "Camera is not ready. Please try again in a moment.",
  "g_0c61ec": "Analyzing face...",
  "g_024d33": "Loading AI model...",
  "g_9dee4d": "AI model loading timeout. Please try again.",
  "g_f9dbb1": "Cannot fetch camera video. Please check camera permissions.",
  "g_31c465": "Could not recognize face. Please look straight into the camera.",
  "g_a97d66": "Failed to save. Please try again.",
  "g_7585c2": "Problem occurred during registration. Please try again.",
  "g_3af9a3": "We don't save photos!",
  "g_f57c15": "Photos are not saved, only encrypted and remembered as 128 numbers. A face cannot be reconstructed from these numbers. (Irreversible)",
  "g_fb2dce": "Once registered, just stand in front of the camera next time to auto check-in!",
  "g_e473b3": "I'll do it next time",
  "g_d94845": "I'll register!",
  "g_b7cf73": "Identity Verification",
  "g_fc483e": "Enter the last 4 digits of your phone number",
  "g_bc539f": "Clear",
  "g_468266": "Confirm",
  "g_c523e4": "Who are you?",
  "g_c03e30": "Multiple members match the entered number",
  "g_96dd03": "Go Back",
  "g_12dbf0": "Please look straight ahead and wait a moment",
  "g_7d4f0a": "Camera Access Denied",
  "g_784896": "Analyzing...",
  "g_0c767c": "Retry",
  "g_74049f": "Registration Complete!",
  "g_e2d423": "Next time you stand in front of the camera, you will be auto checked-in 🎉",
  "g_fb0b11": "📱 App Install Guide",
  "g_a2bcc5": "Add the app to your home screen and launch it directly anytime.",
  "g_c668fe": "We recommend proceeding in the Chrome browser.",
  "g_674c35": "Tap Menu Button",
  "g_06b657": "Press the 3-dot (⋮) menu at the top right of the Chrome browser.",
  "g_103566": "Add to Home Screen",
  "g_88ea49": "From the list, select ",
  "g_f6c3e5": "Install",
  "g_ec5dae": "Check Home Screen",
  "g_996887": "Press the Install button on the screen to create an app icon on your home screen.",
  "g_41b4db": "Only available in Safari browser.",
  "g_6c2f0c": "Tap Share Button",
  "g_f105d0": "Press the Share icon (↑ in square) at the top (or top right) of Safari.",
  "g_d7c24e": "Scroll up the menu and select ",
  "g_ebe4aa": "Add",
  "g_a9ed4a": "At the top right, select ",
  "g_155e2c": "System",
  "g_4f1a01": "Contact Us",
  "g_6b90a5": "Email to receive reply",
  "g_1757a2": "Write your question",
  "g_274cb0": "Send",
  "g_6b044e": "Received!",
  "g_5ccc60": "We will reply via email as soon as possible.",
  "g_1759ce": "Inquire via KakaoTalk",
  "g_574487": "Pending data:",
  "g_752c68": "Free trial ended",
  "g_2bec30": "Studio",
  "g_dc947e": "'s 2-month free trial has expired.",
  "g_190abc": "Continue using all features for $69/year (approx. 100,000 KRW).",
  "g_412424": "🇰🇷 Domestic Wire Transfer (100,000 KRW)",
  "g_fc521b": "MG Saemaeul 9003-2623-9687-7",
  "g_41ceca": "Account Holder: Song Dae-min",
  "g_30d293": "Account number copied.",
  "g_a55b1e": "Copy",
  "g_4ed5f4": "* After deposit, let us know at ",
  "g_c3bb7e": " (or your onboarding contact) to extend your service instantly.",
  "g_53bcaa": "🌍 Global Payment: PayPal ($69)",
  "g_642f63": "⏰ Free Trial D-",
  "g_b5c560": "| Extend for $69/year",
  "g_3b6150": "💳 Extend via PayPal",
  "g_46b103": "❌ This browser does not support notifications. ",
  "g_a8e020": "For iPhone, ",
  "g_490419": "Please use a modern browser like Chrome.",
  "g_cfc84b": "✅ Notifications enabled!",
  "g_7b5319": "❌ Could not fetch token.",
  "g_4cee70": "❌ Notifications blocked. Please allow them in browser settings.",
  "g_63f731": "❌ Notification setup failed: ",
  "g_9cbaec": "ℹ️ You can turn off notifications in browser settings.\nSite Settings > Notifications > Block",
  "g_6bc54d": "ℹ️ iPhone: Click Share (↑) at the bottom of Safari > \\",
  "g_a80316": "ℹ️ Android: Click Browser Menu (⋮) > \\",
  "g_b4df3f": "ℹ️ From the browser menu \\",
  "g_7ba954": "Upcoming",
  "g_cafdc6": "Ended",
  "g_3c5525": " Checked in",
  "g_d4edf3": "Face Matched",
  "g_fc6a3e": "Facial recognition data deleted.",
  "g_2ffd1a": "Click to delete facial data",
  "g_5b426c": "🧠 Face Reg ✕",
  "g_ef43c1": "No attendance data",
  "g_873180": "📋 My class attendance today",
  "g_8038a0": " members)",
  "g_06e61b": "Loading...",
  "g_802f1e": "No classes scheduled for today",
  "g_1d5134": "Select Instructor",
  "g_ee13ad": "Last 4 digits of Phone",
  "g_b63929": "Logging in...",
  "g_e225a6": "Login",
  "g_06057f": "Loading...",
  "g_0b1a0f": "Announcement",
  "g_05d3e2": "No announcements",
  "g_15b744": "New Year",
  "g_b5031f": "Lunar New Year",
  "g_8e793b": "Independence Movement Day",
  "g_f14f6c": "Children's Day",
  "g_e0f35e": "Buddha's Birthday",
  "g_bc3790": "Memorial Day",
  "g_e2084c": "Liberation Day",
  "g_60387c": "Chuseok",
  "g_a32af9": "National Foundation Day",
  "g_cb4424": "Hangul Day",
  "g_7a78ee": "Christmas",
  "g_0b2766": "Election Day",
  "g_b3854d": "Arbor Day",
  "g_0319b6": "👇 Tap a date to view the detailed schedule",
  "g_2b9b17": "📅 View Schedule by Branch",
  "g_a06861": "No classes",
  "g_f20e34": "Cancelled",
  "g_1384ec": "My Classes",
  "g_17f4b4": "Reservation",
  "g_611d6f": "📋 Reservation List",
  "g_f1a05a": "👥 Attendance List",
  "g_fcad99": "Fetching...",
  "g_12c651": "No attendees",
  "g_7c4e80": "Instructor Only",
  "g_2e3374": "After scanning the QR code, ",
  "g_c6d12b": "Last 4 digits of phone number",
  "g_6f02fe": "Enter",
  "g_5435ef": "Clear",
  "g_6e081b": "Korean",
  "g_c12140": "Japanese",
  "g_7be2d2": "Chinese",
  "g_c85116": "AI is thinking",
  "g_6c87b3": "How was your day today?",
  "g_747d3d": "Start Meditation",
  "g_ff9f7e": "Prepared a meditation tailored for you",
  "g_8ea51b": "Directly type your mind state...",
  "g_d5a419": "Meditation Practice Complete",
  "g_b2513d": "AI Mind Observation Journal",
  "g_dd4eb6": "Could not summarize the meditation data analysis.",
  "g_6bbc46": "Breathing Stability",
  "g_158512": "Energy Shift",
  "g_a399c4": "Analyzing meditation data...",
  "g_3a6f82": "Finish Mindfulness and Return",
  "g_fcdc5c": "Volume Control",
  "g_b2579d": "Voice Guide",
  "g_afa4f9": "Ambient Sound",
  "g_7f6b67": "Frequency",
  "g_ad866f": "🔇 Mute All",
  "g_1f048d": "🔊 Unmute",
  "g_9bc1af": "Detecting...",
  "g_ba3b35": "Voice guide is in progress",
  "g_538401": "Data is processed only on the device",
  "g_62cc79": "Sound Control",
  "g_8e9116": "🔊 Press the speaker icon to adjust the volume",
  "g_7b16ec": "(Mindfulness App)",
  "g_93ad3e": "Thinking...",
  "g_7b09c8": "In Voice Chat",
  "g_609c2c": "Start Now",
  "g_54ffd9": "How was your day today?",
  "g_64e81b": "Start Meditation",
  "g_62270b": "Prepared a meditation suited for you",
  "g_9b26b1": "Waiting for answer...",
  "g_a2ecb2": "Type directly...",
  "g_ee2b05": "To keep the surroundings quiet",
  "g_9c7b8c": "Have you set your device to 'Silent' or 'Do Not Disturb' mode <br/>to avoid interruptions?",
  "g_12761e": "Rest assured",
  "g_73b7f2": "Even in 'Silent' or 'Do Not Disturb' mode, **the meditation guide and BGM will play normally.** Only external notifications are blocked, so set it with peace of mind.",
  "g_dd1786": "Confirmed",
  "g_e4bed8": "Today's Meditation",
  "g_c0a38f": "Exit",
  "g_a12a8e": "Where is your mind heading <br/>right now?",
  "g_e36318": "Choose the broad direction of today's meditation",
  "g_17beab": "Shall we look a bit more specifically?",
  "g_e73ad0": "Phone Placement Setup",
  "g_e1011c": "Prop your phone up about 2m away for full-body tracking.",
  "g_2d5c32": "Prop your phone up near your mouth (within 30cm) slightly tilted to detect breathing sounds.",
  "g_f031e4": "Place your phone in a comfortable spot within reach.",
  "g_522c83": "Using earphones with a mic allows for much more accurate breathing sound detection.",
  "g_37934e": "Ready (Start Meditation)",
  "g_a6f7bd": "Looked deeply into your mind's state.",
  "g_c8423c": "AI Mind Analysis",
  "g_b70b05": "Select Meditation Mode",
  "g_cb63e4": "What kind of meditation do you want?",
  "g_29ec81": "Select the mode you need most",
  "g_8c6297": "Meditation Duration",
  "g_53388d": "Nature Sound BGM (On/Off)",
  "g_387e7e": "Prepare for Meditation",
  "g_c7dcff": "Please select the meditation you want",
  "g_832e46": "AI Expert Meditation Prescription",
  "g_ad5238": "AI Psych Analysis Results",
  "g_500870": "Strongly Recommended by AI",
  "g_26a7df": "Full Body Relaxation Guide",
  "g_deb8a5": "Breathing Immersion",
  "g_8c78ca": "Posture Correction",
  "g_a8bf03": "Change Options",
  "g_1deafd": "Body Scan",
  "g_555bfd": "Breathing",
  "g_bb1252": "Posture",
  "g_e9eae1": "BGM",
  "g_d31188": "Start",
  "g_9a6547": "Reselect (Return to Chat)",
  "g_82c0c6": "Environment Detection",
  "g_12fc5f": "How's the weather outside the window right now?",
  "g_68d8b5": "Brain response patterns change depending on the weather",
  "g_343ff0": "Select Meditation",
  "g_08771e": "Please select the state you feel right now",
  "g_f77585": "Cannot check Push Notification status.",
  "g_a324ad": "No Member Information.",
  "g_7ec0c4": "Resetting Push Notifications...",
  "g_e2f0dc": "Checking Push Notification Status...",
  "g_e2739a": "Push Notification Settings",
  "g_f5c404": "Browser Support:",
  "g_673cbb": "✓ Supported",
  "g_424c5e": "✗ Unsupported",
  "g_62a4fa": "Alert Permission:",
  "g_e9eefe": "✓ Allowed",
  "g_773bf7": "✗ Blocked",
  "g_aa002b": "○ Unset",
  "g_d6a0d7": "✓ Enabled",
  "g_b06352": "✗ Disabled",
  "g_00a7be": "Push Token:",
  "g_7d4a6e": "✓ Registered",
  "g_171a52": "✗ Unregistered",
  "g_b8b24a": "Please allow notifications in your browser settings:",
  "g_92dc2f": "Click the padlock (🔒) icon on the left of the address bar",
  "g_996454": "Change Notifications → Allow",
  "g_d24ae5": "Refresh the page, then click the button below",
  "g_32c087": "To receive push notifications, press the button below to complete the setup.",
  "g_5868a8": "Resetting...",
  "g_ddca5b": "Reset Push Notifications",
  "g_74db6c": "Push Notifications have been set up successfully.",
  "g_cb3f23": "Reset",
  "g_c99a30": "An error occurred during cancellation processing",
  "g_f91285": "Capacity",
  "g_afcbc1": "Cancel Waitlist",
  "g_7f40dc": "Cancel Reservation",
  "g_78841d": "Join Waitlist",
  "g_27a026": "Fully Booked",
  "g_379fdd": "Reserve",
  "g_380d11": "Self-Practice",
  "g_1dbb24": "My Reservations",
  "g_4727c6": "Practice recording temporarily paused",
  "g_bc913b": "No records",
  "g_8ebcf3": "Insufficient data",
  "g_6fee74": "Analyzing",
  "g_3951e7": "System Maint",
  "g_179052": "Gap Occurred",
  "g_75a591": "GapOccurred",
  "g_c542d2": "Lack of Data",
  "g_0daea1": "No Record",
  "g_6c4c42": "Recorded as Rest",
  "g_3a3717": "Rest State",
  "g_920e33": "Rest Occurred",
  "g_18575c": "6 PM",
  "g_5d3b6b": "8 PM",
  "g_f922d7": "Congestion by Branch",
  "g_ff0fac": "Based on last 4 weeks of check-ins · Visit during quiet hours!",
  "g_03a5b8": "If I visit now?",
  "g_d2b108": "Recommended Visit Time",
  "g_f33ee1": "Loading AI Recommendations...",
  "g_f228b5": "Cloudy",
  "g_7120b7": "Rain",
  "g_0726db": "Snow",
  "g_507b55": "Today's 3-Min Home Workout",
  "g_23eb27": "Language",
  "g_a484b5": "Kim Bang-mun",
  "g_f52787": "🚀 Quick Start Demo Account",
  "g_4f0782": "💠 AI Check-in Registration",
  "g_aa0cc0": "AI Check-in Info",
  "g_7487f8": "— \n                        Your photos are",
  "g_d4206d": "not saved.",
  "g_898d03": "Facial features are converted into a 128-dimensional number (vector) and stored safely. Original images are deleted instantly. Faces cannot be restored from the numerical data.",
  "g_c06b16": "Restart on First Check-in",
  "g_f8fc36": "Fast",
  "g_773a61": "You're working hard! Keep it up at this pace!",
  "g_b777db": "Proper",
  "g_491a53": "Perfect pace! Consistency is the secret to health!",
  "g_21460f": "Slightly Slow",
  "g_a16508": "Push a bit more to make the most of your membership!",
  "g_d7a0cb": "Slow",
  "g_a95871": "Come practice! You still have plenty of time left to do it!",
  "g_77813b": "Pace",
  "g_200a34": " Used /",
  "g_0fd568": " Out of ",
  "g_75600e": "Attendance",
  "g_1528ad": "Perfect diligence! You are a yoga master 🧘♀️",
  "g_8266c4": "Excellent! A practitioner shining with consistency",
  "g_0a5a3c": "Good pace! Just a bit more regularly",
  "g_c8db70": "There's potential! Try to build a habit",
  "g_24fb8a": "Let's start again! From a small step",
  "g_3deaf3": "Weekly Check-ins",
  "g_88d2d2": "Regularity",
  "g_bab125": "Very Regular",
  "g_d82985": "Regular",
  "g_7582c5": "Irregular",
  "g_58a92c": "Consistency",
  "g_b8ffad": "Recent Vitality",
  "g_91e95d": "Diligence Score",
  "g_207753": " pts / 100",
  "g_556228": "Bottom",
  "g_c4c7f1": "Click Share Button",
  "g_59a092": "Account number copied.",
  "g_58a303": "This browser does not support the copy feature. Please select and copy the text manually.",
  "g_9ce64c": "📋 Copy",
  "g_c6f3dc": "Health Report",
  "g_a38216": "Avg Heart Rate",
  "g_969659": "Workout Time",
  "g_b9ffd3": "Max Heart Rate",
  "g_0b877b": " Mins",
  "g_363c34": "Unregistered",
  "g_453d0d": "Level",
  "g_f6846c": "Normal",
  "g_ce0109": "Change",
  "g_d2e531": "Manage Instructors & Class Types",
  "g_d57caf": "Instructor List",
  "g_85525d": "💡 Click on an instructor to edit their phone number",
  "g_c3c6fb": "Instructor Name",
  "g_9c73bc": "Phone (Optional)",
  "g_99b155": "Failed to add instructor",
  "g_579429": "Add",
  "g_41b08f": "Failed to save phone number",
  "g_11685b": "Click to enter phone number",
  "g_f3e768": "Failed to delete instructor",
  "g_abd084": "Class Type",
  "g_11600c": " Items",
  "g_9d77d9": "Enter class type",
  "g_791b55": "Failed to add class type",
  "g_3aadfe": "Failed to delete class type",
  "g_7b61bb": "Class Level",
  "g_7e6fdf": "For classes with levels",
  "g_7198ea": "Enter level (e.g., 0, 0.5, 1)",
  "g_708764": "Level already exists.",
  "g_061d94": "Failed to add class level",
  "g_dbdc54": "スタジオ準備中...",
  "g_24d026": "工作室加载中...",
  "g_d84ded": "You are a top-tier B2B yoga studio management consultant. Provide a comprehensive management briefing to the Director.\nPlease cover all these areas:\n1. 📊 Revenue Analysis: Monthly revenue, daily trend, MoM changes\n2. 👥 Member Management: Active/Total ratio, New vs. Renewal, Expiration risk strategy\n3. 🔄 Renewal Rate Deep-Dive: Cumulative vs. Recent 3-months, Monthly trends, Improvement strategies\n4. ⚠️ Churn Prevention: Expired/Denied status, Proactive retention strategy\n5. 👩🏫 Instructor Evaluation & HR: Class participation per instructor, Popular vs. Needs-attention instructors, Schedule optimization\n6. 📱 Digital Transformation: App install rate, Push reach analysis, Digital marketing opportunities\n7. 🔮 Future Outlook: Next month forecast based on current trends, Seasonality, Proactive measures\n\nTone: Professional and actionable. Backed by numbers and facts. 4~6 paragraphs.\nNever fabricate data for areas with missing metrics. Only analyze based on actual data provided.",
  "g_3390c3": "You are a top-tier yoga/fitness studio management consultant. Provide a comprehensive management briefing to the Owner.\nPlease cover the following areas:\n1. 📊 Revenue Analysis: Monthly revenue, daily trend, MoM changes\n2. 👥 Member Management: Active/Total ratio, New vs. Renewal, Expiration risk strategy\n3. 🔄 Renewal Rate Analysis: Cumulative vs. Recent 3-months, Monthly trends\n4. ⚠️ Churn Prevention: Expired/Denied status, Proactive retention strategy\n5. 👩🏫 Instructor Evaluation: Class participation per instructor, Popular vs. Needs-attention instructors\n6. 📱 Digital Transformation: App install rate, Push reach analysis\n7. 🔮 Future Outlook: Next month forecast based on current trends\n\nTone: Professional and actionable. Backed by data and logic. 4-6 paragraphs.\nDo not fabricate data for empty areas. Analyze only with actual data.",
  "g_3bbd84": "Pre-Class (Morning)",
  "g_99b3d6": "During AM Class",
  "g_92e742": "During PM Class",
  "g_ba5587": "It's the afternoon peak hour. Please analyze real-time attendance, remaining classes, and today's trends.",
  "g_5ccaee": "Post-Class (Evening)",
  "g_db5d55": "Today's classes have wrapped up. Please compile a comprehensive report on the day's performance.",
  "g_6127c0": "授業前（朝）",
  "g_33b6ee": "午前の授業中",
  "g_6747b9": "午前の授業が進行中です。現在までの出席状況と午後の予定を分析してください。",
  "g_82016d": "午後の授業中",
  "g_c46ead": "午後のピーク時間帯です。リアルタイムの出席状況と今日のトレンドを分析してください。",
  "g_0e242a": "終了後（夜）",
  "g_913577": "本日の授業は終了しました。一日の総合レポートをまとめてください。",
  "g_e3de55": "Error during approval: ",
  "g_04c18b": "Are you sure you want to delete (reject) this scheduled send?",
  "g_e2492d": "Error during deletion: ",
  "g_06e329": "An error occurred during data analysis.",
  "g_65812d": "Start Date",
  "g_f3ce23": "Memo",
  "g_e5e21e": "No changes made.",
  "g_c9e7b4": "\n\n※ Revenue records are managed separately and remain unaffected.",
  "g_aafa04": "You have unsaved changes. Discard changes and close window?",
  "g_1ec9ff": "Manual Confirm",
  "g_5500af": "Manual check-in completed.",
  "g_7e55e8": "Check-in failed: ",
  "g_a40f19": "Check-in failed.",
  "g_1a60a7": "Are you sure you want to delete?",
  "g_3f74e1": "Delete Failed",
  "g_540235": "Meditation",
  "g_c497b8": "Peaceful",
  "g_86597c": "A bit exhausted",
  "g_7bfb74": "Complicated",
  "g_159cf6": "Connection is slightly delayed. Shall we continue talking?",
  "g_657a80": "How did you feel today?",
  "g_858158": "Yes, sounds good",
  "g_a8c969": "I'll think about it for a moment",
  "g_6ceafa": "So-so",
  "g_e88580": "Exhausted",
  "g_e44766": "Sorry, connection is unstable. Shall we continue chatting?",
  "g_242fb0": "I'll just start",
  "g_7bee58": "Go to Home",
  "g_93949f": "Yes, I'll start",
  "g_37396e": "Start Customized Meditation",
  "g_12daec": "I want to meditate",
  "g_80cfa5": "I will start",
  "g_abcda1": "Start Meditation",
  "g_629e3c": "Connection is delayed",
  "g_f43cd6": "Connection is unstable",
  "g_d7fbec": "Yes, I do",
  "g_249065": "It's fine, I'll meditate",
  "g_691ffa": "Meditation observation journal is not ready.",
  "g_6acb87": "Morning to start the day,",
  "g_8e3a90": "Afternoon when energy is needed,",
  "g_d545af": "Night to wrap up the day,",
  "g_5fde0b": "Highly Regular",
  "g_fa06c1": "Regular",
  "g_6ef51b": "Irregular",
  "g_4b29d0": "useMemberUI — Integration Test (RTL renderHook)",
  "g_8f1d5c": "Initial activeTab is \\",
  "g_6dc4e2": "Switch tab using setActiveTab",
  "g_5e9af9": "greetingVisible initial true + toggle",
  "g_f876a2": "Delete?",
  "g_9faf4d": "loginForm initial values + setLoginFormValue",
  "g_d2b17c": "Hong Gil-dong",
  "g_7fd6e3": "scheduleView default is calendar",
  "g_c6b53f": "lightboxImage initial null + setting",
  "g_3db7b0": "installGuide modal Open/Close",
  "g_c42221": "selectedNoticeId initial null + setting",
  "g_699948": "scheduleBranch default is gwangheungchang",
  "g_427f22": "scheduleMonth default is current",
  "g_b2719c": "Membership",
  "g_b28fbe": "New Year's Day",
  "g_980e4b": "Lunar New Year",
  "g_81e731": "Independence Movement Day",
  "g_3119a6": "Children's Day",
  "g_3b47f2": "Buddha's Birthday",
  "g_30e15a": "Delete",
  "g_ebccbc": "Exit Admin Mode?",
  "g_08f9a3": "Failed to change image count.",
  "g_af67a3": "File size is too large. (Max 5MB)",
  "g_14affc": "Image upload failed. (Ensure it is 5MB or less)",
  "g_9564f6": ",\r\n          phone: ",
  "g_25340e": "Deleted or missing member.",
  "g_ee2134": "Error occurred while saving sales record.",
  "g_ba6718": "Turned off notifications on this device. (Browser permissions are maintained)",
  "g_f3382b": "Registered to receive remote push notifications.",
  "g_a9bba7": "Push notification permission denied. Please allow it in browser settings.",
  "g_fa5cf7": "Problem occurred during notification setup.",
  "g_cb22c9": "AI Send Proposal (Pending Approval)",
  "g_c90b3e": "Proposal for ",
  "g_0d80f6": "Reason:",
  "g_044bb1": "Member Needing Care",
  "g_fe5b40": "Greeting Message",
  "g_dcb51c": "Approve & Send",
  "g_119476": "Pricing Overview (Image)",
  "g_848c41": "Image Count:",
  "g_58426f": "1 Image",
  "g_4c7458": "2 Images",
  "g_8a0e7a": "3 Images",
  "g_59e9cd": "Pricing Image",
  "g_35964c": "Pricing",
  "g_94b6ad": "No image registered",
  "g_c9ab86": "Change Pricing",
  "g_2dc2b9": "Invalid request. Please check if the link is correct.",
  "g_ace592": "Expired or invalid password reset link. Please ask the Director to issue a new link.",
  "g_b126b0": "Unsupported authentication mode: ",
  "g_0406bb": "Password must be at least 6 characters.",
  "g_2bb826": "Passwords do not match.",
  "g_07d3fc": "Password change failed: ",
  "g_75df3a": "Verifying authentication info...",
  "g_bd6abd": "Access Error",
  "g_964d15": "Return to Login Screen",
  "g_7fea9c": "Password Setup Complete!",
  "g_27e600": "Congratulations. Admin account password successfully set.",
  "g_13663e": "Log in right now",
  "g_3bf293": "Set Admin Password",
  "g_665558": "Welcome!",
  "g_a2c1cc": "account's",
  "g_b75aba": "Please set a new password.",
  "g_5a7ef7": "New Password (6+ chars)",
  "g_6ce978": "Enter secure password",
  "g_768b58": "Confirm Password",
  "g_711154": "Re-enter password",
  "g_1754bd": "Setting up...",
  "g_60568d": "Save Password & Complete",
  "g_a81959": "Checking in...",
  "g_ebb526": "Visiting Member",
  "g_1f7776": "Will guide you to a peaceful yoga session today. Namaste 🙏",
  "g_04cdab": "😔 Unregistered number",
  "g_f7866f": "⏳ Membership Expired",
  "g_2d2816": "Membership duration has passed or passes depleted.\n\nPlease contact the front desk.",
  "g_752d87": "❌ Check-in Failed",
  "g_7c1dfd": "A temporary error occurred.\nPlease try again in a moment.",
  "g_34c5fc": "⚠️ System Error",
  "g_c2c12e": "A temporary system error occurred.\nPlease try again in a moment.",
  "g_69c40d": "Good morning",
  "g_0afaa0": "Good afternoon today too",
  "g_3b6240": "Great work",
  "g_71a096": "Start of a new week!",
  "g_7e763e": "Happy Friday!",
  "g_81cdb0": "Happy Weekend!",
  "g_b163f5": "Log out?",
  "g_e11dab": "Setting up",
  "g_162678": "Alerts ON",
  "g_e0bda3": "Alerts OFF",
  "g_bc08bf": "AI is preparing today's greeting",
  "g_13a46f": "Home",
  "g_72ffa1": "Schedule/Reservations",
  "g_78222f": "Schedule",
  "g_339679": "Privacy Policy",
  "g_f61acd": "Failed to load AI engine. Please check your network.",
  "g_1d81e4": "[Session] AI consecutive failures — Switching at 35s intervals",
  "g_9fec66": "Microphone permission is required.",
  "g_d9b2a4": "Camera permission is required. Please allow camera access in settings.",
  "g_fc4231": "Breathe in deeply and exhale, your peaceful time begins.",
  "g_4a6ff0": "A bit unfortunate, but that's okay. Let's start exactly as you feel now. 🙏",
  "g_519521": "Feeling",
  "g_8875c3": "Considers people and relationships first",
  "g_29cf93": "Lifestyle",
  "g_88d56b": "Judging",
  "g_42f541": "Planned and systematic lifestyle",
  "g_e4b268": "Perceiving",
  "g_d093ac": "Flexible and free lifestyle",
  "g_d98339": "Setting up...",
  "g_306384": "Health Data Sync",
  "g_67ba8d": "Apple/Samsung Health Connected",
  "g_49e5a2": "HR/Calorie tracking management",
  "g_0ccf9f": "My MBTI",
  "g_34061b": " — Reflected in AI greetings and tailored coaching",
  "g_13000c": "Set it up to receive your own AI greetings and coaching ✨",
  "g_76520e": " Complete ✓",
  "g_2aacea": "Reselect",
  "g_5381fd": "Privacy Policy",
  "g_c77cb7": "Studio has been created instantly!",
  "g_4fd543": "✅ 2-month free trial has started",
  "g_b56ead": "Go straight to my studio",
  "g_95623d": "This Service",
  "g_b99c6e": " (hereafter \\",
  "g_e5baa9": "Article 1 (Purpose of Processing Personal Data)",
  "g_3b93c2": "The Company processes personal data for the following purposes. Personal data being processed is not used for purposes other than the following, and if the purpose of use changes, necessary actions such as obtaining separate consent will be implemented.",
  "g_708618": "Member Registration & Management: Confirming intent to join, verifying identity for membership service provision, maintaining/managing membership status",
  "g_1e1e93": "Class Attendance Management: Confirming class check-ins and history, managing remaining passes",
  "g_07c561": "Facial Recognition Check-in: Collecting/processing facial feature data for contactless check-ins (upon consent)",
  "g_c11d37": "Service Improvement: Analyzing service usage statistics and improving service quality",
  "g_881717": "Notices/Alerts: Sending essential alerts like class schedule changes and closure notices",
  "g_09d2fa": "Article 2 (Personal Data Items Processed)",
  "g_3d1ae0": "The Company processes the following personal data items.",
  "g_fd926e": "Required Items:",
  "g_3d27d1": "Name, Contact (Phone), Membership payment and usage records (Payment method, Amount, etc.)",
  "g_52de11": "Optional Items:",
  "g_6d0f11": "Date of Birth, Gender, Memos such as vulnerable physical areas",
  "g_b40930": "Automatically Collected Items:",
  "g_936ae9": "Check-in time, Reservation and practice history, Service usage records",
  "g_7842c1": "Upon Facial Recognition Consent:",
  "g_a0ea7f": "Facial feature vector (Numerical data) — Original photos are not saved, and it is technically impossible to restore original photos from numerical data",
  "g_3b4b2d": "Special Rule for Children's Personal Data:",
  "g_ee2957": "When registering a member under 14 years old, we may additionally collect the name and contact of the legal representative (e.g., parents) to go through the legal representative's consent procedure.",
  "g_3d6396": "Article 3 (Processing and Retention Period of Personal Data)",
  "g_dd8f0d": "The Company processes and retains personal data within the statutory retention/usage period or the retention/usage period agreed upon when collecting personal data from the data subject.",
  "g_e4b30f": "Member Registration Info:",
  "g_a25750": "Until membership withdrawal",
  "g_9ed7b1": "(Destroyed immediately upon withdrawal)",
  "g_dd126d": "Check-in and Practice History:",
  "g_b4c53b": "1 year from the last usage date",
  "g_105402": "Facial Feature Data:",
  "g_e2713b": "Destroyed immediately upon withdrawal",
  "g_970bac": "Article 4 (Provision of Personal Data to Third Parties)",
  "g_cf1c56": "The Company processes the data subject's personal data only within the scope specified in Article 1, and does not provide personal data to third parties except with the data subject's consent or special provisions of laws.",
  "g_3b33b8": "Article 5 (Outsourcing of Personal Data Processing)",
  "g_89e745": "To provide smooth and improved services, the Company outsources personal data processing to external experts as follows. When signing an outsourcing contract, we clearly define compliance with privacy guidelines and legal responsibilities.",
  "g_0f8315": "System Maintenance & Server Operation:",
  "g_986c6e": "Notification Message Send:",
  "g_edfee2": "Alimtalk & SMS Dispatch Agency",
  "g_4f8dd4": "Electronic Payment Processing:",
  "g_445e6f": "Payment Gateway (PG) & Card Companies",
  "g_d54207": "Article 6 (Installation/Operation and Refusal of Auto Data Collection Devices)",
  "g_203560": "The Company stores and frequently retrieves usage info to provide users with a convenient connection environment (like keeping simple logins) ",
  "g_a1316d": "Refusal of Installation/Operation:",
  "g_30cce7": "You can block data storage in your device or browser settings, but personalized services like auto-login may become unavailable.",
  "g_2b17de": "Article 7 (Measures for Securing Personal Data Safety)",
  "g_b30778": "The Company takes the following measures to ensure the safety of personal data.",
  "g_45d284": "Data Encryption:",
  "g_dee1c0": "Personal data is saved encrypted using AES-256 and transmitted encrypted via SSL/TLS",
  "g_6a3e30": "Access Control:",
  "g_153e4a": "Access to personal data is controlled via admin authentication (password)",
  "g_534e94": "Cloud Security:",
  "g_4f2420": "We use Google Cloud Platform (Firebase) infrastructure, protecting data according to Google's security standards",
  "g_f054d2": "Minimal Collection Principle:",
  "g_78aa20": "We only collect the minimum personal data necessary for the service",
  "g_16cd6c": "Article 8 (Rights, Obligations, and Exercise Methods of Data Subjects)",
  "g_e98c08": "The data subject may exercise the following personal data privacy rights against the Company at any time.",
  "g_1fda95": "Request access to personal data",
  "g_e93cd0": "Request correction if errors exist",
  "g_044778": "Request deletion",
  "g_64f267": "Request suspension of processing",
  "g_00a42f": "These rights can be exercised via written, phone, or network communication, and the Company will take immediate action.",
  "g_e389bb": "This Privacy Policy applies from the effective date, and any additions, deletions, or corrections according to laws and policies will be notified via announcements 7 days before enforcement.",
  "g_47d1cf": "This policy",
  "g_da8e28": "takes effect from.",
  "g_774275": "Failed to load inquiries:",
  "g_81a184": "Translation failed:",
  "g_84fd49": "Failed to load admin list: ",
  "g_c5156e": "Email and role are required.",
  "g_00693f": "General Admins must select a branch.",
  "g_1265fc": "Email send failed (ignored):",
  "g_60c58a": "Creation failed: ",
  "g_5eeba8": "Error Occurred",
  "g_be3a8d": "Password must be at least 6 characters.",
  "g_2b68d8": "g_2b68d8",
  "g_b126c0": "📦 Plan:",
  "g_17292f": "Free Trial",
  "g_d053f5": "📥 Attachment #",
  "g_612ca2": "Download",
  "g_edb1cf": "📥 Download Attachment (1)",
  "g_6c3c44": "Press this button to auto-setup the Director's exclusive DB and send a KakaoTalk alert.",
  "g_350916": "✅ Approve & Issue ID",
  "g_0b6761": "Reject if fake or duplicate application.",
  "g_457da6": "❌ Reject",
  "g_963144": "Registered Studio List",
  "g_ae1d1f": "Currently Online",
  "g_813c28": "Click to edit Start (Creation) Date.",
  "g_9f6303": "🗓️ Start Date:",
  "g_1feee3": "No Date",
  "g_e51551": "g_e51551",
  "g_1c631d": "g_1c631d",
  "g_5fc089": "⛔ Trial Expired",
  "g_162657": "👥 Members",
  "g_83c5a3": "📦 Registration Attachment",
  "g_b62339": "📦 Download Registration Attachment",
  "g_2538d9": "New Admin",
  "g_b79209": "New Admin Setup Flow (Super Admin Hidden Mode)",
  "g_22877c": "At the top right, click ",
  "g_5e19ff": "[+ New Admin]",
  "g_0fcb13": " button",
  "g_d043d7": "g_7d9e3a",
  "g_7d9e3a": "Select email and assigned branch only, then \\",
  "g_05990c": "Once successful, on the screen",
  "g_11ad7f": "g_8b7d1e",
  "g_8b7d1e": "\\",
  "g_4169bb": "Create",
  "g_71e171": "Press this Copy Link button and send to the Director via KakaoTalk/SMS",
  "g_82c8bc": "Director clicks the link, enters their own password, and saves",
  "g_2904f9": "Display Name",
  "g_4dec08": "E.g.: Director Kim",
  "g_c90de7": "Role *",
  "g_3c9eb9": "🔒 General Admin (Specific branch only)",
  "g_8241e3": "👑 Super Admin (All branches)",
  "g_d1a82e": "Assigned Branch *",
  "g_c074e1": "Select Branch...",
  "g_f37390": "🔐 Password is set directly by the Admin. A setup link will be provided after creation.",
  "g_1c54a5": "Creating...",
  "g_612ee1": "✅ Create",
  "g_3cebae": "Register New Studio",
  "g_344a41": "Studio ID *",
  "g_7a2317": "E.g.: namaste-yoga",
  "g_8d1071": "Lowercase English, numbers, and hyphens only",
  "g_2b5eb5": "Studio Name *",
  "g_bd1eb6": "E.g.: Namaste Yoga",
  "g_dea9f2": "Admin Email *",
  "g_e21a14": "Registering...",
  "g_1ebbc6": "🏢 Register",
  "g_dcce5d": "List of pre-empted Firebase Hosting domains. Outsiders cannot claim these.",
  "g_ace280": "Active",
  "g_1378bb": "Boksaem Yoga",
  "g_a20f83": "Ssangmun Yoga",
  "g_b25ed4": "Reserved",
  "g_cadba1": "Boksaem Yoga (Append)",
  "g_f6947c": "Mapo Yoga",
  "g_1954aa": "Mapo Yoga (Append)",
  "g_131dc3": "Gongdeok Yoga",
  "g_39bc10": "Gongdeok Yoga (Append)",
  "g_8fba09": "Ahyeon Yoga",
  "g_a73991": "Ahyeon Yoga (Append)",
  "g_346453": "Ewha Yoga",
  "g_dd49f2": "Ewha Yoga (Append)",
  "g_28b0c0": "Sinchon Yoga",
  "g_137714": "Sinchon Yoga (Append)",
  "g_66479b": "Hongdae Yoga",
  "g_5c2870": "Hongdae Yoga (Append)",
  "g_3865af": "Mangwon Yoga",
  "g_807211": "Mangwon Yoga (Append)",
  "g_5dae47": "Hapjeong Yoga",
  "g_e17925": "Hapjeong Yoga (Append)",
  "g_11da0f": "Aeogae Yoga",
  "g_e9a912": "Aeogae Yoga (Append)",
  "g_79cc63": "Yeouido Yoga",
  "g_55dfb0": "Yeouido Yoga (Append)",
  "g_14858e": "PassFlow Landing"
}